{"date":"2026-06-05","period_days":30,"overall":{"total_runs":95,"total_tokens":87294844,"total_action_minutes":942},"workflows":[{"workflow_name":"Matt Pocock Skills Reviewer","run_count":6,"total_tokens":7219579,"avg_tokens":1203263,"total_turns":134,"total_action_minutes":76,"error_count":0,"warning_count":0},{"workflow_name":"Sergo - Serena Go Expert","run_count":1,"total_tokens":7150313,"avg_tokens":7150313,"total_turns":86,"total_action_minutes":23,"error_count":1,"warning_count":0},{"workflow_name":"Daily Rendering Scripts Verifier","run_count":1,"total_tokens":6889805,"avg_tokens":6889805,"total_turns":81,"total_action_minutes":15,"error_count":0,"warning_count":0},{"workflow_name":"Test Quality Sentinel","run_count":6,"total_tokens":6354409,"avg_tokens":1059068,"total_turns":192,"total_action_minutes":70,"error_count":1,"warning_count":0},{"workflow_name":"Safe Output Health Monitor","run_count":1,"total_tokens":4249168,"avg_tokens":4249168,"total_turns":66,"total_action_minutes":12,"error_count":0,"warning_count":0},{"workflow_name":"Daily OTel Instrumentation Advisor","run_count":1,"total_tokens":4039001,"avg_tokens":4039001,"total_turns":41,"total_action_minutes":13,"error_count":0,"warning_count":0},{"workflow_name":"Daily AgentRx Trace Optimizer","run_count":1,"total_tokens":3602747,"avg_tokens":3602747,"total_turns":38,"total_action_minutes":15,"error_count":0,"warning_count":0},{"workflow_name":"Contribution Check","run_count":2,"total_tokens":3545952,"avg_tokens":1772976,"total_turns":115,"total_action_minutes":29,"error_count":1,"warning_count":0},{"workflow_name":"Instructions Janitor","run_count":1,"total_tokens":3352317,"avg_tokens":3352317,"total_turns":63,"total_action_minutes":12,"error_count":0,"warning_count":0},{"workflow_name":"Daily AW Cross-Repo Compile Check","run_count":1,"total_tokens":2816222,"avg_tokens":2816222,"total_turns":45,"total_action_minutes":22,"error_count":0,"warning_count":0},{"workflow_name":"GitHub API Consumption Report Agent","run_count":1,"total_tokens":2785320,"avg_tokens":2785320,"total_turns":35,"total_action_minutes":16,"error_count":0,"warning_count":0},{"workflow_name":"Package Specification Extractor","run_count":1,"total_tokens":2576977,"avg_tokens":2576977,"total_turns":36,"total_action_minutes":12,"error_count":1,"warning_count":0},{"workflow_name":"Code Simplifier","run_count":1,"total_tokens":2485436,"avg_tokens":2485436,"total_turns":51,"total_action_minutes":13,"error_count":1,"warning_count":0},{"workflow_name":"Sub-Issue Closer","run_count":1,"total_tokens":2430700,"avg_tokens":2430700,"total_turns":53,"total_action_minutes":14,"error_count":0,"warning_count":0},{"workflow_name":"Design Decision Gate \ud83c\udfd7\ufe0f","run_count":6,"total_tokens":2329786,"avg_tokens":388298,"total_turns":39,"total_action_minutes":33,"error_count":0,"warning_count":0},{"workflow_name":"Copilot Session Insights","run_count":1,"total_tokens":2314029,"avg_tokens":2314029,"total_turns":30,"total_action_minutes":31,"error_count":0,"warning_count":0},{"workflow_name":"Static Analysis Report","run_count":1,"total_tokens":1892859,"avg_tokens":1892859,"total_turns":25,"total_action_minutes":12,"error_count":0,"warning_count":0},{"workflow_name":"Daily CLI Tools Exploratory Tester","run_count":1,"total_tokens":1892655,"avg_tokens":1892655,"total_turns":35,"total_action_minutes":19,"error_count":0,"warning_count":0},{"workflow_name":"PR Sous Chef","run_count":5,"total_tokens":1851995,"avg_tokens":370399,"total_turns":85,"total_action_minutes":43,"error_count":0,"warning_count":0},{"workflow_name":"Step Name Alignment","run_count":1,"total_tokens":1788619,"avg_tokens":1788619,"total_turns":30,"total_action_minutes":8,"error_count":0,"warning_count":0},{"workflow_name":"Terminal Stylist","run_count":1,"total_tokens":1434419,"avg_tokens":1434419,"total_turns":27,"total_action_minutes":13,"error_count":0,"warning_count":0},{"workflow_name":"Glossary Maintainer","run_count":1,"total_tokens":1421561,"avg_tokens":1421561,"total_turns":23,"total_action_minutes":11,"error_count":0,"warning_count":0},{"workflow_name":"Daily A/B Testing Advisor","run_count":1,"total_tokens":1325210,"avg_tokens":1325210,"total_turns":42,"total_action_minutes":15,"error_count":0,"warning_count":0},{"workflow_name":"[aw] Failure Investigator (6h)","run_count":1,"total_tokens":1196615,"avg_tokens":1196615,"total_turns":23,"total_action_minutes":14,"error_count":0,"warning_count":0},{"workflow_name":"CLI Version Checker","run_count":1,"total_tokens":1103783,"avg_tokens":1103783,"total_turns":21,"total_action_minutes":9,"error_count":0,"warning_count":0},{"workflow_name":"Daily Hippo Learn","run_count":1,"total_tokens":1075716,"avg_tokens":1075716,"total_turns":28,"total_action_minutes":10,"error_count":0,"warning_count":0},{"workflow_name":"Go Fan","run_count":1,"total_tokens":1032857,"avg_tokens":1032857,"total_turns":30,"total_action_minutes":8,"error_count":0,"warning_count":0},{"workflow_name":"Workflow Health Manager - Meta-Orchestrator","run_count":1,"total_tokens":980723,"avg_tokens":980723,"total_turns":25,"total_action_minutes":11,"error_count":0,"warning_count":0},{"workflow_name":"Daily AstroStyleLite Markdown Spellcheck","run_count":1,"total_tokens":858480,"avg_tokens":858480,"total_turns":15,"total_action_minutes":8,"error_count":0,"warning_count":0},{"workflow_name":"Multi-Device Docs Tester","run_count":1,"total_tokens":719813,"avg_tokens":719813,"total_turns":17,"total_action_minutes":9,"error_count":0,"warning_count":0},{"workflow_name":"Refactoring Cadence","run_count":1,"total_tokens":618112,"avg_tokens":618112,"total_turns":20,"total_action_minutes":9,"error_count":0,"warning_count":0},{"workflow_name":"Schema Consistency Checker","run_count":1,"total_tokens":596982,"avg_tokens":596982,"total_turns":9,"total_action_minutes":7,"error_count":0,"warning_count":0},{"workflow_name":"Dependabot Dependency Checker","run_count":1,"total_tokens":518518,"avg_tokens":518518,"total_turns":10,"total_action_minutes":7,"error_count":0,"warning_count":0},{"workflow_name":"Daily Semgrep Scan","run_count":1,"total_tokens":452432,"avg_tokens":452432,"total_turns":16,"total_action_minutes":7,"error_count":0,"warning_count":0},{"workflow_name":"OTLP Data Quality Validator","run_count":1,"total_tokens":434293,"avg_tokens":434293,"total_turns":11,"total_action_minutes":7,"error_count":0,"warning_count":0},{"workflow_name":"Issue Monster","run_count":1,"total_tokens":346369,"avg_tokens":346369,"total_turns":12,"total_action_minutes":6,"error_count":0,"warning_count":0},{"workflow_name":"Daily Safe Outputs Conformance Checker","run_count":1,"total_tokens":343080,"avg_tokens":343080,"total_turns":8,"total_action_minutes":5,"error_count":0,"warning_count":0},{"workflow_name":"GPL Dependency Cleaner (gpclean)","run_count":1,"total_tokens":326021,"avg_tokens":326021,"total_turns":10,"total_action_minutes":5,"error_count":0,"warning_count":0},{"workflow_name":"Daily Choice Type Test","run_count":1,"total_tokens":249683,"avg_tokens":249683,"total_turns":5,"total_action_minutes":5,"error_count":0,"warning_count":0},{"workflow_name":"Dependabot Burner","run_count":1,"total_tokens":199605,"avg_tokens":199605,"total_turns":7,"total_action_minutes":5,"error_count":0,"warning_count":0},{"workflow_name":"Auto-Triage Issues","run_count":1,"total_tokens":198807,"avg_tokens":198807,"total_turns":10,"total_action_minutes":7,"error_count":0,"warning_count":0},{"workflow_name":"PR Description Updater","run_count":1,"total_tokens":126839,"avg_tokens":126839,"total_turns":6,"total_action_minutes":5,"error_count":0,"warning_count":0},{"workflow_name":"GitHub Remote MCP Authentication Test","run_count":1,"total_tokens":115134,"avg_tokens":115134,"total_turns":5,"total_action_minutes":3,"error_count":0,"warning_count":0},{"workflow_name":"Dependabot Campaign","run_count":1,"total_tokens":51903,"avg_tokens":51903,"total_turns":3,"total_action_minutes":4,"error_count":0,"warning_count":0},{"workflow_name":"PR Code Quality Reviewer","run_count":6,"total_tokens":0,"avg_tokens":0,"total_turns":6,"total_action_minutes":67,"error_count":1,"warning_count":0},{"workflow_name":"Smoke CI","run_count":6,"total_tokens":0,"avg_tokens":0,"total_turns":0,"total_action_minutes":22,"error_count":0,"warning_count":0},{"workflow_name":"Draft PR Cleanup","run_count":1,"total_tokens":0,"avg_tokens":0,"total_turns":1,"total_action_minutes":7,"error_count":0,"warning_count":0},{"workflow_name":"Daily Documentation Updater","run_count":1,"total_tokens":0,"avg_tokens":0,"total_turns":1,"total_action_minutes":4,"error_count":1,"warning_count":0},{"workflow_name":"Copilot PR Conversation NLP Analysis","run_count":1,"total_tokens":0,"avg_tokens":0,"total_turns":1,"total_action_minutes":17,"error_count":0,"warning_count":0},{"workflow_name":"Daily MCP Tool Concurrency Analysis","run_count":1,"total_tokens":0,"avg_tokens":0,"total_turns":1,"total_action_minutes":7,"error_count":0,"warning_count":0},{"workflow_name":"Dev","run_count":1,"total_tokens":0,"avg_tokens":0,"total_turns":0,"total_action_minutes":8,"error_count":0,"warning_count":0},{"workflow_name":"Daily Syntax Error Quality Check","run_count":1,"total_tokens":0,"avg_tokens":0,"total_turns":1,"total_action_minutes":6,"error_count":0,"warning_count":0},{"workflow_name":"Daily Workflow Updater","run_count":1,"total_tokens":0,"avg_tokens":0,"total_turns":0,"total_action_minutes":3,"error_count":1,"warning_count":0},{"workflow_name":"PR Triage Agent","run_count":1,"total_tokens":0,"avg_tokens":0,"total_turns":1,"total_action_minutes":7,"error_count":0,"warning_count":0},{"workflow_name":"Daily News","run_count":1,"total_tokens":0,"avg_tokens":0,"total_turns":0,"total_action_minutes":7,"error_count":1,"warning_count":0},{"workflow_name":"Duplicate Code Detector","run_count":1,"total_tokens":0,"avg_tokens":0,"total_turns":0,"total_action_minutes":6,"error_count":0,"warning_count":0},{"workflow_name":"Copilot Agent Prompt Clustering Analysis","run_count":1,"total_tokens":0,"avg_tokens":0,"total_turns":1,"total_action_minutes":26,"error_count":0,"warning_count":0},{"workflow_name":"daily-experiment-report","run_count":1,"total_tokens":0,"avg_tokens":0,"total_turns":1,"total_action_minutes":12,"error_count":0,"warning_count":0},{"workflow_name":"AI Moderator","run_count":2,"total_tokens":0,"avg_tokens":0,"total_turns":0,"total_action_minutes":29,"error_count":0,"warning_count":0},{"workflow_name":"Designer Drift Audit","run_count":1,"total_tokens":0,"avg_tokens":0,"total_turns":0,"total_action_minutes":2,"error_count":1,"warning_count":0},{"workflow_name":"Documentation Noob Tester","run_count":1,"total_tokens":0,"avg_tokens":0,"total_turns":1,"total_action_minutes":9,"error_count":0,"warning_count":0},{"workflow_name":"jsweep - JavaScript Unbloater","run_count":1,"total_tokens":0,"avg_tokens":0,"total_turns":1,"total_action_minutes":5,"error_count":0,"warning_count":0},{"workflow_name":"Copilot CLI Deep Research Agent","run_count":1,"total_tokens":0,"avg_tokens":0,"total_turns":1,"total_action_minutes":15,"error_count":1,"warning_count":0},{"workflow_name":"Deployment Incident Monitor","run_count":1,"total_tokens":0,"avg_tokens":0,"total_turns":1,"total_action_minutes":5,"error_count":0,"warning_count":0}]}